processor/mem.v
module mem #(parameter filename = "ram.hex")
          (input clock, we,
           input [7:0] address,
           inout [7:0] data);

  reg [7:0] RAM[0:255];

  initial
    // $readmemh(filename, RAM); //Hex file
    $readmemb(filename, RAM); //Bin file

  assign data = we ? 'bz : RAM[address]; 

  always @(posedge clock)
    if (we) RAM[address] <= data;
endmodule

processor/cpu.v
module uP(
  input clock, reset,
  inout [7:0] mbr,
  output logic we,
  output logic [7:0] mar, pc, ir);
  
  parameter FETCH = 0, DECODE = 1, EXECUTE = 2;
  reg [1:0] state, nextstate;
  reg [7:0] acc;
  
  always @(posedge clock or posedge reset)
  begin
    if (reset) begin
      pc = 'b0;
      state <= FETCH;
    end
    else begin
      case(state)
      FETCH: begin
        we <= 0;
        pc <= pc + 1;
        mar <= pc;
      end
      DECODE: begin
        ir = mbr;
        mar <= {4'b1111, ir[3:0]};
      end
      EXECUTE: begin
        if (ir[7] == 1'b1)           // jump
          pc <= {1'b0, ir[6:0]};
        else if (ir[7:4] == 4'b0100) // indirect load 
          acc <= mbr;
        else if (ir[7:4] == 4'b0101) // add acc + data
          acc <= acc + mbr;
        else if (ir[7:4] == 4'b0011) // store
          we <= 1'b1;
      end
      endcase  
      state <= nextstate;                  
    end
  end
  
  always @(*)
    case(state)
      FETCH:   nextstate = DECODE;
      DECODE:  nextstate = EXECUTE;
      EXECUTE: nextstate = FETCH;
      default: nextstate = FETCH; 
    endcase
  
  assign mbr = we ? acc : 'bz;
endmodule

processor/top.v
module up_tb;
  reg clock, reset;
  wire we;
  wire [7:0] address, ir, pc, data;
  
  uP proc(clock, reset, data, we, address, pc, ir);
//  mem #("fibo.hex") ram(clock, we, address, data); 
  mem #("fibo.bin") ram(clock, we, address, data); 
  
  initial
    begin
      $dumpfile("dump.vcd"); $dumpvars(0);
      reset <= 1; #22; reset <= 0;
      #5000; $finish;
    end

  always
    begin
      clock <= 1; #5; clock <= 0; #5;
    end
endmodule

processor/dump.vcd
$date
	Fri Nov 25 08:50:33 2022
$end
$version
	Icarus Verilog
$end
$timescale
	1s
$end
$scope module up_tb $end
$var wire 8 ! data [7:0] $end
$var wire 1 " we $end
$var wire 8 # pc [7:0] $end
$var wire 8 $ ir [7:0] $end
$var wire 8 % address [7:0] $end
$var reg 1 & clock $end
$var reg 1 ' reset $end
$scope module proc $end
$var wire 1 & clock $end
$var wire 8 ( mbr [7:0] $end
$var wire 1 ' reset $end
$var reg 8 ) acc [7:0] $end
$var reg 8 * ir [7:0] $end
$var reg 8 + mar [7:0] $end
$var reg 2 , nextstate [1:0] $end
$var reg 8 - pc [7:0] $end
$var reg 2 . state [1:0] $end
$var reg 1 " we $end
$upscope $end
$scope module ram $end
$var wire 8 / address [7:0] $end
$var wire 1 & clock $end
$var wire 8 0 data [7:0] $end
$var wire 1 " we $end
$upscope $end
$upscope $end
$enddefinitions $end
#0
$dumpvars
bx 0
bx /
b0 .
b0 -
b1 ,
bx +
bx *
bx )
bx (
1'
1&
bx %
bx $
b0 #
x"
bx !
$end
#5
0&
#10
1&
#15
0&
#20
1&
#22
0'
#25
0&
#30
b10 ,
b1000000 !
b1000000 (
b1000000 0
b1 .
b0 %
b0 +
b0 /
b1 #
b1 -
0"
1&
#35
0&
#40
b0 ,
b0 !
b0 (
b0 0
b10 .
b11110000 %
b11110000 +
b11110000 /
b1000000 $
b1000000 *
1&
#45
0&
#50
b1 ,
b0 .
b0 )
1&
#55
0&
#60
b10 ,
b1010001 !
b1010001 (
b1010001 0
b1 .
b1 %
b1 +
b1 /
b10 #
b10 -
1&
#65
0&
#70
b0 ,
b1 !
b1 (
b1 0
b10 .
b11110001 %
b11110001 +
b11110001 /
b1010001 $
b1010001 *
1&
#75
0&
#80
b1 ,
b0 .
b1 )
1&
#85
0&
#90
b10 ,
b110010 !
b110010 (
b110010 0
b1 .
b10 %
b10 +
b10 /
b11 #
b11 -
1&
#95
0&
#100
b0 ,
b0 !
b0 (
b0 0
b10 .
b11110010 %
b11110010 +
b11110010 /
b110010 $
b110010 *
1&
#105
0&
#110
b1 ,
b1 !
b1 (
b1 0
b0 .
1"
1&
#115
0&
#120
b10 ,
b1000001 !
b1000001 (
b1000001 0
b1 .
b11 %
b11 +
b11 /
b100 #
b100 -
0"
1&
#125
0&
#130
b0 ,
b1 !
b1 (
b1 0
b10 .
b11110001 %
b11110001 +
b11110001 /
b1000001 $
b1000001 *
1&
#135
0&
#140
b1 ,
b0 .
1&
#145
0&
#150
b10 ,
b110000 !
b110000 (
b110000 0
b1 .
b100 %
b100 +
b100 /
b101 #
b101 -
1&
#155
0&
#160
b0 ,
b0 !
b0 (
b0 0
b10 .
b11110000 %
b11110000 +
b11110000 /
b110000 $
b110000 *
1&
#165
0&
#170
b1 ,
b1 !
b1 (
b1 0
b0 .
1"
1&
#175
0&
#180
b10 ,
b1000010 !
b1000010 (
b1000010 0
b1 .
b101 %
b101 +
b101 /
b110 #
b110 -
0"
1&
#185
0&
#190
b0 ,
b1 !
b1 (
b1 0
b10 .
b11110010 %
b11110010 +
b11110010 /
b1000010 $
b1000010 *
1&
#195
0&
#200
b1 ,
b0 .
1&
#205
0&
#210
b10 ,
b110001 !
b110001 (
b110001 0
b1 .
b110 %
b110 +
b110 /
b111 #
b111 -
1&
#215
0&
#220
b0 ,
b1 !
b1 (
b1 0
b10 .
b11110001 %
b11110001 +
b11110001 /
b110001 $
b110001 *
1&
#225
0&
#230
b1 ,
b1 !
b1 (
b1 0
b0 .
1"
1&
#235
0&
#240
b10 ,
b10000000 !
b10000000 (
b10000000 0
b1 .
b111 %
b111 +
b111 /
b1000 #
b1000 -
0"
1&
#245
0&
#250
b0 ,
b1 !
b1 (
b1 0
b10 .
b11110000 %
b11110000 +
b11110000 /
b10000000 $
b10000000 *
1&
#255
0&
#260
b1 ,
b0 .
b0 #
b0 -
1&
#265
0&
#270
b10 ,
b1000000 !
b1000000 (
b1000000 0
b1 .
b0 %
b0 +
b0 /
b1 #
b1 -
1&
#275
0&
#280
b0 ,
b1 !
b1 (
b1 0
b10 .
b11110000 %
b11110000 +
b11110000 /
b1000000 $
b1000000 *
1&
#285
0&
#290
b1 ,
b0 .
1&
#295
0&
#300
b10 ,
b1010001 !
b1010001 (
b1010001 0
b1 .
b1 %
b1 +
b1 /
b10 #
b10 -
1&
#305
0&
#310
b0 ,
b1 !
b1 (
b1 0
b10 .
b11110001 %
b11110001 +
b11110001 /
b1010001 $
b1010001 *
1&
#315
0&
#320
b1 ,
b0 .
b10 )
1&
#325
0&
#330
b10 ,
b110010 !
b110010 (
b110010 0
b1 .
b10 %
b10 +
b10 /
b11 #
b11 -
1&
#335
0&
#340
b0 ,
b1 !
b1 (
b1 0
b10 .
b11110010 %
b11110010 +
b11110010 /
b110010 $
b110010 *
1&
#345
0&
#350
b1 ,
b10 !
b10 (
b10 0
b0 .
1"
1&
#355
0&
#360
b10 ,
b1000001 !
b1000001 (
b1000001 0
b1 .
b11 %
b11 +
b11 /
b100 #
b100 -
0"
1&
#365
0&
#370
b0 ,
b1 !
b1 (
b1 0
b10 .
b11110001 %
b11110001 +
b11110001 /
b1000001 $
b1000001 *
1&
#375
0&
#380
b1 ,
b0 .
b1 )
1&
#385
0&
#390
b10 ,
b110000 !
b110000 (
b110000 0
b1 .
b100 %
b100 +
b100 /
b101 #
b101 -
1&
#395
0&
#400
b0 ,
b1 !
b1 (
b1 0
b10 .
b11110000 %
b11110000 +
b11110000 /
b110000 $
b110000 *
1&
#405
0&
#410
b1 ,
b1 !
b1 (
b1 0
b0 .
1"
1&
#415
0&
#420
b10 ,
b1000010 !
b1000010 (
b1000010 0
b1 .
b101 %
b101 +
b101 /
b110 #
b110 -
0"
1&
#425
0&
#430
b0 ,
b10 !
b10 (
b10 0
b10 .
b11110010 %
b11110010 +
b11110010 /
b1000010 $
b1000010 *
1&
#435
0&
#440
b1 ,
b0 .
b10 )
1&
#445
0&
#450
b10 ,
b110001 !
b110001 (
b110001 0
b1 .
b110 %
b110 +
b110 /
b111 #
b111 -
1&
#455
0&
#460
b0 ,
b1 !
b1 (
b1 0
b10 .
b11110001 %
b11110001 +
b11110001 /
b110001 $
b110001 *
1&
#465
0&
#470
b1 ,
b10 !
b10 (
b10 0
b0 .
1"
1&
#475
0&
#480
b10 ,
b10000000 !
b10000000 (
b10000000 0
b1 .
b111 %
b111 +
b111 /
b1000 #
b1000 -
0"
1&
#485
0&
#490
b0 ,
b1 !
b1 (
b1 0
b10 .
b11110000 %
b11110000 +
b11110000 /
b10000000 $
b10000000 *
1&
#495
0&
#500
b1 ,
b0 .
b0 #
b0 -
1&
#505
0&
#510
b10 ,
b1000000 !
b1000000 (
b1000000 0
b1 .
b0 %
b0 +
b0 /
b1 #
b1 -
1&
#515
0&
#520
b0 ,
b1 !
b1 (
b1 0
b10 .
b11110000 %
b11110000 +
b11110000 /
b1000000 $
b1000000 *
1&
#525
0&
#530
b1 ,
b0 .
b1 )
1&
#535
0&
#540
b10 ,
b1010001 !
b1010001 (
b1010001 0
b1 .
b1 %
b1 +
b1 /
b10 #
b10 -
1&
#545
0&
#550
b0 ,
b10 !
b10 (
b10 0
b10 .
b11110001 %
b11110001 +
b11110001 /
b1010001 $
b1010001 *
1&
#555
0&
#560
b1 ,
b0 .
b11 )
1&
#565
0&
#570
b10 ,
b110010 !
b110010 (
b110010 0
b1 .
b10 %
b10 +
b10 /
b11 #
b11 -
1&
#575
0&
#580
b0 ,
b10 !
b10 (
b10 0
b10 .
b11110010 %
b11110010 +
b11110010 /
b110010 $
b110010 *
1&
#585
0&
#590
b1 ,
b11 !
b11 (
b11 0
b0 .
1"
1&
#595
0&
#600
b10 ,
b1000001 !
b1000001 (
b1000001 0
b1 .
b11 %
b11 +
b11 /
b100 #
b100 -
0"
1&
#605
0&
#610
b0 ,
b10 !
b10 (
b10 0
b10 .
b11110001 %
b11110001 +
b11110001 /
b1000001 $
b1000001 *
1&
#615
0&
#620
b1 ,
b0 .
b10 )
1&
#625
0&
#630
b10 ,
b110000 !
b110000 (
b110000 0
b1 .
b100 %
b100 +
b100 /
b101 #
b101 -
1&
#635
0&
#640
b0 ,
b1 !
b1 (
b1 0
b10 .
b11110000 %
b11110000 +
b11110000 /
b110000 $
b110000 *
1&
#645
0&
#650
b1 ,
b10 !
b10 (
b10 0
b0 .
1"
1&
#655
0&
#660
b10 ,
b1000010 !
b1000010 (
b1000010 0
b1 .
b101 %
b101 +
b101 /
b110 #
b110 -
0"
1&
#665
0&
#670
b0 ,
b11 !
b11 (
b11 0
b10 .
b11110010 %
b11110010 +
b11110010 /
b1000010 $
b1000010 *
1&
#675
0&
#680
b1 ,
b0 .
b11 )
1&
#685
0&
#690
b10 ,
b110001 !
b110001 (
b110001 0
b1 .
b110 %
b110 +
b110 /
b111 #
b111 -
1&
#695
0&
#700
b0 ,
b10 !
b10 (
b10 0
b10 .
b11110001 %
b11110001 +
b11110001 /
b110001 $
b110001 *
1&
#705
0&
#710
b1 ,
b11 !
b11 (
b11 0
b0 .
1"
1&
#715
0&
#720
b10 ,
b10000000 !
b10000000 (
b10000000 0
b1 .
b111 %
b111 +
b111 /
b1000 #
b1000 -
0"
1&
#725
0&
#730
b0 ,
b10 !
b10 (
b10 0
b10 .
b11110000 %
b11110000 +
b11110000 /
b10000000 $
b10000000 *
1&
#735
0&
#740
b1 ,
b0 .
b0 #
b0 -
1&
#745
0&
#750
b10 ,
b1000000 !
b1000000 (
b1000000 0
b1 .
b0 %
b0 +
b0 /
b1 #
b1 -
1&
#755
0&
#760
b0 ,
b10 !
b10 (
b10 0
b10 .
b11110000 %
b11110000 +
b11110000 /
b1000000 $
b1000000 *
1&
#765
0&
#770
b1 ,
b0 .
b10 )
1&
#775
0&
#780
b10 ,
b1010001 !
b1010001 (
b1010001 0
b1 .
b1 %
b1 +
b1 /
b10 #
b10 -
1&
#785
0&
#790
b0 ,
b11 !
b11 (
b11 0
b10 .
b11110001 %
b11110001 +
b11110001 /
b1010001 $
b1010001 *
1&
#795
0&
#800
b1 ,
b0 .
b101 )
1&
#805
0&
#810
b10 ,
b110010 !
b110010 (
b110010 0
b1 .
b10 %
b10 +
b10 /
b11 #
b11 -
1&
#815
0&
#820
b0 ,
b11 !
b11 (
b11 0
b10 .
b11110010 %
b11110010 +
b11110010 /
b110010 $
b110010 *
1&
#825
0&
#830
b1 ,
b101 !
b101 (
b101 0
b0 .
1"
1&
#835
0&
#840
b10 ,
b1000001 !
b1000001 (
b1000001 0
b1 .
b11 %
b11 +
b11 /
b100 #
b100 -
0"
1&
#845
0&
#850
b0 ,
b11 !
b11 (
b11 0
b10 .
b11110001 %
b11110001 +
b11110001 /
b1000001 $
b1000001 *
1&
#855
0&
#860
b1 ,
b0 .
b11 )
1&
#865
0&
#870
b10 ,
b110000 !
b110000 (
b110000 0
b1 .
b100 %
b100 +
b100 /
b101 #
b101 -
1&
#875
0&
#880
b0 ,
b10 !
b10 (
b10 0
b10 .
b11110000 %
b11110000 +
b11110000 /
b110000 $
b110000 *
1&
#885
0&
#890
b1 ,
b11 !
b11 (
b11 0
b0 .
1"
1&
#895
0&
#900
b10 ,
b1000010 !
b1000010 (
b1000010 0
b1 .
b101 %
b101 +
b101 /
b110 #
b110 -
0"
1&
#905
0&
#910
b0 ,
b101 !
b101 (
b101 0
b10 .
b11110010 %
b11110010 +
b11110010 /
b1000010 $
b1000010 *
1&
#915
0&
#920
b1 ,
b0 .
b101 )
1&
#925
0&
#930
b10 ,
b110001 !
b110001 (
b110001 0
b1 .
b110 %
b110 +
b110 /
b111 #
b111 -
1&
#935
0&
#940
b0 ,
b11 !
b11 (
b11 0
b10 .
b11110001 %
b11110001 +
b11110001 /
b110001 $
b110001 *
1&
#945
0&
#950
b1 ,
b101 !
b101 (
b101 0
b0 .
1"
1&
#955
0&
#960
b10 ,
b10000000 !
b10000000 (
b10000000 0
b1 .
b111 %
b111 +
b111 /
b1000 #
b1000 -
0"
1&
#965
0&
#970
b0 ,
b11 !
b11 (
b11 0
b10 .
b11110000 %
b11110000 +
b11110000 /
b10000000 $
b10000000 *
1&
#975
0&
#980
b1 ,
b0 .
b0 #
b0 -
1&
#985
0&
#990
b10 ,
b1000000 !
b1000000 (
b1000000 0
b1 .
b0 %
b0 +
b0 /
b1 #
b1 -
1&
#995
0&
#1000
b0 ,
b11 !
b11 (
b11 0
b10 .
b11110000 %
b11110000 +
b11110000 /
b1000000 $
b1000000 *
1&
#1005
0&
#1010
b1 ,
b0 .
b11 )
1&
#1015
0&
#1020
b10 ,
b1010001 !
b1010001 (
b1010001 0
b1 .
b1 %
b1 +
b1 /
b10 #
b10 -
1&
#1025
0&
#1030
b0 ,
b101 !
b101 (
b101 0
b10 .
b11110001 %
b11110001 +
b11110001 /
b1010001 $
b1010001 *
1&
#1035
0&
#1040
b1 ,
b0 .
b1000 )
1&
#1045
0&
#1050
b10 ,
b110010 !
b110010 (
b110010 0
b1 .
b10 %
b10 +
b10 /
b11 #
b11 -
1&
#1055
0&
#1060
b0 ,
b101 !
b101 (
b101 0
b10 .
b11110010 %
b11110010 +
b11110010 /
b110010 $
b110010 *
1&
#1065
0&
#1070
b1 ,
b1000 !
b1000 (
b1000 0
b0 .
1"
1&
#1075
0&
#1080
b10 ,
b1000001 !
b1000001 (
b1000001 0
b1 .
b11 %
b11 +
b11 /
b100 #
b100 -
0"
1&
#1085
0&
#1090
b0 ,
b101 !
b101 (
b101 0
b10 .
b11110001 %
b11110001 +
b11110001 /
b1000001 $
b1000001 *
1&
#1095
0&
#1100
b1 ,
b0 .
b101 )
1&
#1105
0&
#1110
b10 ,
b110000 !
b110000 (
b110000 0
b1 .
b100 %
b100 +
b100 /
b101 #
b101 -
1&
#1115
0&
#1120
b0 ,
b11 !
b11 (
b11 0
b10 .
b11110000 %
b11110000 +
b11110000 /
b110000 $
b110000 *
1&
#1125
0&
#1130
b1 ,
b101 !
b101 (
b101 0
b0 .
1"
1&
#1135
0&
#1140
b10 ,
b1000010 !
b1000010 (
b1000010 0
b1 .
b101 %
b101 +
b101 /
b110 #
b110 -
0"
1&
#1145
0&
#1150
b0 ,
b1000 !
b1000 (
b1000 0
b10 .
b11110010 %
b11110010 +
b11110010 /
b1000010 $
b1000010 *
1&
#1155
0&
#1160
b1 ,
b0 .
b1000 )
1&
#1165
0&
#1170
b10 ,
b110001 !
b110001 (
b110001 0
b1 .
b110 %
b110 +
b110 /
b111 #
b111 -
1&
#1175
0&
#1180
b0 ,
b101 !
b101 (
b101 0
b10 .
b11110001 %
b11110001 +
b11110001 /
b110001 $
b110001 *
1&
#1185
0&
#1190
b1 ,
b1000 !
b1000 (
b1000 0
b0 .
1"
1&
#1195
0&
#1200
b10 ,
b10000000 !
b10000000 (
b10000000 0
b1 .
b111 %
b111 +
b111 /
b1000 #
b1000 -
0"
1&
#1205
0&
#1210
b0 ,
b101 !
b101 (
b101 0
b10 .
b11110000 %
b11110000 +
b11110000 /
b10000000 $
b10000000 *
1&
#1215
0&
#1220
b1 ,
b0 .
b0 #
b0 -
1&
#1225
0&
#1230
b10 ,
b1000000 !
b1000000 (
b1000000 0
b1 .
b0 %
b0 +
b0 /
b1 #
b1 -
1&
#1235
0&
#1240
b0 ,
b101 !
b101 (
b101 0
b10 .
b11110000 %
b11110000 +
b11110000 /
b1000000 $
b1000000 *
1&
#1245
0&
#1250
b1 ,
b0 .
b101 )
1&
#1255
0&
#1260
b10 ,
b1010001 !
b1010001 (
b1010001 0
b1 .
b1 %
b1 +
b1 /
b10 #
b10 -
1&
#1265
0&
#1270
b0 ,
b1000 !
b1000 (
b1000 0
b10 .
b11110001 %
b11110001 +
b11110001 /
b1010001 $
b1010001 *
1&
#1275
0&
#1280
b1 ,
b0 .
b1101 )
1&
#1285
0&
#1290
b10 ,
b110010 !
b110010 (
b110010 0
b1 .
b10 %
b10 +
b10 /
b11 #
b11 -
1&
#1295
0&
#1300
b0 ,
b1000 !
b1000 (
b1000 0
b10 .
b11110010 %
b11110010 +
b11110010 /
b110010 $
b110010 *
1&
#1305
0&
#1310
b1 ,
b1101 !
b1101 (
b1101 0
b0 .
1"
1&
#1315
0&
#1320
b10 ,
b1000001 !
b1000001 (
b1000001 0
b1 .
b11 %
b11 +
b11 /
b100 #
b100 -
0"
1&
#1325
0&
#1330
b0 ,
b1000 !
b1000 (
b1000 0
b10 .
b11110001 %
b11110001 +
b11110001 /
b1000001 $
b1000001 *
1&
#1335
0&
#1340
b1 ,
b0 .
b1000 )
1&
#1345
0&
#1350
b10 ,
b110000 !
b110000 (
b110000 0
b1 .
b100 %
b100 +
b100 /
b101 #
b101 -
1&
#1355
0&
#1360
b0 ,
b101 !
b101 (
b101 0
b10 .
b11110000 %
b11110000 +
b11110000 /
b110000 $
b110000 *
1&
#1365
0&
#1370
b1 ,
b1000 !
b1000 (
b1000 0
b0 .
1"
1&
#1375
0&
#1380
b10 ,
b1000010 !
b1000010 (
b1000010 0
b1 .
b101 %
b101 +
b101 /
b110 #
b110 -
0"
1&
#1385
0&
#1390
b0 ,
b1101 !
b1101 (
b1101 0
b10 .
b11110010 %
b11110010 +
b11110010 /
b1000010 $
b1000010 *
1&
#1395
0&
#1400
b1 ,
b0 .
b1101 )
1&
#1405
0&
#1410
b10 ,
b110001 !
b110001 (
b110001 0
b1 .
b110 %
b110 +
b110 /
b111 #
b111 -
1&
#1415
0&
#1420
b0 ,
b1000 !
b1000 (
b1000 0
b10 .
b11110001 %
b11110001 +
b11110001 /
b110001 $
b110001 *
1&
#1425
0&
#1430
b1 ,
b1101 !
b1101 (
b1101 0
b0 .
1"
1&
#1435
0&
#1440
b10 ,
b10000000 !
b10000000 (
b10000000 0
b1 .
b111 %
b111 +
b111 /
b1000 #
b1000 -
0"
1&
#1445
0&
#1450
b0 ,
b1000 !
b1000 (
b1000 0
b10 .
b11110000 %
b11110000 +
b11110000 /
b10000000 $
b10000000 *
1&
#1455
0&
#1460
b1 ,
b0 .
b0 #
b0 -
1&
#1465
0&
#1470
b10 ,
b1000000 !
b1000000 (
b1000000 0
b1 .
b0 %
b0 +
b0 /
b1 #
b1 -
1&
#1475
0&
#1480
b0 ,
b1000 !
b1000 (
b1000 0
b10 .
b11110000 %
b11110000 +
b11110000 /
b1000000 $
b1000000 *
1&
#1485
0&
#1490
b1 ,
b0 .
b1000 )
1&
#1495
0&
#1500
b10 ,
b1010001 !
b1010001 (
b1010001 0
b1 .
b1 %
b1 +
b1 /
b10 #
b10 -
1&
#1505
0&
#1510
b0 ,
b1101 !
b1101 (
b1101 0
b10 .
b11110001 %
b11110001 +
b11110001 /
b1010001 $
b1010001 *
1&
#1515
0&
#1520
b1 ,
b0 .
b10101 )
1&
#1525
0&
#1530
b10 ,
b110010 !
b110010 (
b110010 0
b1 .
b10 %
b10 +
b10 /
b11 #
b11 -
1&
#1535
0&
#1540
b0 ,
b1101 !
b1101 (
b1101 0
b10 .
b11110010 %
b11110010 +
b11110010 /
b110010 $
b110010 *
1&
#1545
0&
#1550
b1 ,
b10101 !
b10101 (
b10101 0
b0 .
1"
1&
#1555
0&
#1560
b10 ,
b1000001 !
b1000001 (
b1000001 0
b1 .
b11 %
b11 +
b11 /
b100 #
b100 -
0"
1&
#1565
0&
#1570
b0 ,
b1101 !
b1101 (
b1101 0
b10 .
b11110001 %
b11110001 +
b11110001 /
b1000001 $
b1000001 *
1&
#1575
0&
#1580
b1 ,
b0 .
b1101 )
1&
#1585
0&
#1590
b10 ,
b110000 !
b110000 (
b110000 0
b1 .
b100 %
b100 +
b100 /
b101 #
b101 -
1&
#1595
0&
#1600
b0 ,
b1000 !
b1000 (
b1000 0
b10 .
b11110000 %
b11110000 +
b11110000 /
b110000 $
b110000 *
1&
#1605
0&
#1610
b1 ,
b1101 !
b1101 (
b1101 0
b0 .
1"
1&
#1615
0&
#1620
b10 ,
b1000010 !
b1000010 (
b1000010 0
b1 .
b101 %
b101 +
b101 /
b110 #
b110 -
0"
1&
#1625
0&
#1630
b0 ,
b10101 !
b10101 (
b10101 0
b10 .
b11110010 %
b11110010 +
b11110010 /
b1000010 $
b1000010 *
1&
#1635
0&
#1640
b1 ,
b0 .
b10101 )
1&
#1645
0&
#1650
b10 ,
b110001 !
b110001 (
b110001 0
b1 .
b110 %
b110 +
b110 /
b111 #
b111 -
1&
#1655
0&
#1660
b0 ,
b1101 !
b1101 (
b1101 0
b10 .
b11110001 %
b11110001 +
b11110001 /
b110001 $
b110001 *
1&
#1665
0&
#1670
b1 ,
b10101 !
b10101 (
b10101 0
b0 .
1"
1&
#1675
0&
#1680
b10 ,
b10000000 !
b10000000 (
b10000000 0
b1 .
b111 %
b111 +
b111 /
b1000 #
b1000 -
0"
1&
#1685
0&
#1690
b0 ,
b1101 !
b1101 (
b1101 0
b10 .
b11110000 %
b11110000 +
b11110000 /
b10000000 $
b10000000 *
1&
#1695
0&
#1700
b1 ,
b0 .
b0 #
b0 -
1&
#1705
0&
#1710
b10 ,
b1000000 !
b1000000 (
b1000000 0
b1 .
b0 %
b0 +
b0 /
b1 #
b1 -
1&
#1715
0&
#1720
b0 ,
b1101 !
b1101 (
b1101 0
b10 .
b11110000 %
b11110000 +
b11110000 /
b1000000 $
b1000000 *
1&
#1725
0&
#1730
b1 ,
b0 .
b1101 )
1&
#1735
0&
#1740
b10 ,
b1010001 !
b1010001 (
b1010001 0
b1 .
b1 %
b1 +
b1 /
b10 #
b10 -
1&
#1745
0&
#1750
b0 ,
b10101 !
b10101 (
b10101 0
b10 .
b11110001 %
b11110001 +
b11110001 /
b1010001 $
b1010001 *
1&
#1755
0&
#1760
b1 ,
b0 .
b100010 )
1&
#1765
0&
#1770
b10 ,
b110010 !
b110010 (
b110010 0
b1 .
b10 %
b10 +
b10 /
b11 #
b11 -
1&
#1775
0&
#1780
b0 ,
b10101 !
b10101 (
b10101 0
b10 .
b11110010 %
b11110010 +
b11110010 /
b110010 $
b110010 *
1&
#1785
0&
#1790
b1 ,
b100010 !
b100010 (
b100010 0
b0 .
1"
1&
#1795
0&
#1800
b10 ,
b1000001 !
b1000001 (
b1000001 0
b1 .
b11 %
b11 +
b11 /
b100 #
b100 -
0"
1&
#1805
0&
#1810
b0 ,
b10101 !
b10101 (
b10101 0
b10 .
b11110001 %
b11110001 +
b11110001 /
b1000001 $
b1000001 *
1&
#1815
0&
#1820
b1 ,
b0 .
b10101 )
1&
#1825
0&
#1830
b10 ,
b110000 !
b110000 (
b110000 0
b1 .
b100 %
b100 +
b100 /
b101 #
b101 -
1&
#1835
0&
#1840
b0 ,
b1101 !
b1101 (
b1101 0
b10 .
b11110000 %
b11110000 +
b11110000 /
b110000 $
b110000 *
1&
#1845
0&
#1850
b1 ,
b10101 !
b10101 (
b10101 0
b0 .
1"
1&
#1855
0&
#1860
b10 ,
b1000010 !
b1000010 (
b1000010 0
b1 .
b101 %
b101 +
b101 /
b110 #
b110 -
0"
1&
#1865
0&
#1870
b0 ,
b100010 !
b100010 (
b100010 0
b10 .
b11110010 %
b11110010 +
b11110010 /
b1000010 $
b1000010 *
1&
#1875
0&
#1880
b1 ,
b0 .
b100010 )
1&
#1885
0&
#1890
b10 ,
b110001 !
b110001 (
b110001 0
b1 .
b110 %
b110 +
b110 /
b111 #
b111 -
1&
#1895
0&
#1900
b0 ,
b10101 !
b10101 (
b10101 0
b10 .
b11110001 %
b11110001 +
b11110001 /
b110001 $
b110001 *
1&
#1905
0&
#1910
b1 ,
b100010 !
b100010 (
b100010 0
b0 .
1"
1&
#1915
0&
#1920
b10 ,
b10000000 !
b10000000 (
b10000000 0
b1 .
b111 %
b111 +
b111 /
b1000 #
b1000 -
0"
1&
#1925
0&
#1930
b0 ,
b10101 !
b10101 (
b10101 0
b10 .
b11110000 %
b11110000 +
b11110000 /
b10000000 $
b10000000 *
1&
#1935
0&
#1940
b1 ,
b0 .
b0 #
b0 -
1&
#1945
0&
#1950
b10 ,
b1000000 !
b1000000 (
b1000000 0
b1 .
b0 %
b0 +
b0 /
b1 #
b1 -
1&
#1955
0&
#1960
b0 ,
b10101 !
b10101 (
b10101 0
b10 .
b11110000 %
b11110000 +
b11110000 /
b1000000 $
b1000000 *
1&
#1965
0&
#1970
b1 ,
b0 .
b10101 )
1&
#1975
0&
#1980
b10 ,
b1010001 !
b1010001 (
b1010001 0
b1 .
b1 %
b1 +
b1 /
b10 #
b10 -
1&
#1985
0&
#1990
b0 ,
b100010 !
b100010 (
b100010 0
b10 .
b11110001 %
b11110001 +
b11110001 /
b1010001 $
b1010001 *
1&
#1995
0&
#2000
b1 ,
b0 .
b110111 )
1&
#2005
0&
#2010
b10 ,
b110010 !
b110010 (
b110010 0
b1 .
b10 %
b10 +
b10 /
b11 #
b11 -
1&
#2015
0&
#2020
b0 ,
b100010 !
b100010 (
b100010 0
b10 .
b11110010 %
b11110010 +
b11110010 /
b110010 $
b110010 *
1&
#2025
0&
#2030
b1 ,
b110111 !
b110111 (
b110111 0
b0 .
1"
1&
#2035
0&
#2040
b10 ,
b1000001 !
b1000001 (
b1000001 0
b1 .
b11 %
b11 +
b11 /
b100 #
b100 -
0"
1&
#2045
0&
#2050
b0 ,
b100010 !
b100010 (
b100010 0
b10 .
b11110001 %
b11110001 +
b11110001 /
b1000001 $
b1000001 *
1&
#2055
0&
#2060
b1 ,
b0 .
b100010 )
1&
#2065
0&
#2070
b10 ,
b110000 !
b110000 (
b110000 0
b1 .
b100 %
b100 +
b100 /
b101 #
b101 -
1&
#2075
0&
#2080
b0 ,
b10101 !
b10101 (
b10101 0
b10 .
b11110000 %
b11110000 +
b11110000 /
b110000 $
b110000 *
1&
#2085
0&
#2090
b1 ,
b100010 !
b100010 (
b100010 0
b0 .
1"
1&
#2095
0&
#2100
b10 ,
b1000010 !
b1000010 (
b1000010 0
b1 .
b101 %
b101 +
b101 /
b110 #
b110 -
0"
1&
#2105
0&
#2110
b0 ,
b110111 !
b110111 (
b110111 0
b10 .
b11110010 %
b11110010 +
b11110010 /
b1000010 $
b1000010 *
1&
#2115
0&
#2120
b1 ,
b0 .
b110111 )
1&
#2125
0&
#2130
b10 ,
b110001 !
b110001 (
b110001 0
b1 .
b110 %
b110 +
b110 /
b111 #
b111 -
1&
#2135
0&
#2140
b0 ,
b100010 !
b100010 (
b100010 0
b10 .
b11110001 %
b11110001 +
b11110001 /
b110001 $
b110001 *
1&
#2145
0&
#2150
b1 ,
b110111 !
b110111 (
b110111 0
b0 .
1"
1&
#2155
0&
#2160
b10 ,
b10000000 !
b10000000 (
b10000000 0
b1 .
b111 %
b111 +
b111 /
b1000 #
b1000 -
0"
1&
#2165
0&
#2170
b0 ,
b100010 !
b100010 (
b100010 0
b10 .
b11110000 %
b11110000 +
b11110000 /
b10000000 $
b10000000 *
1&
#2175
0&
#2180
b1 ,
b0 .
b0 #
b0 -
1&
#2185
0&
#2190
b10 ,
b1000000 !
b1000000 (
b1000000 0
b1 .
b0 %
b0 +
b0 /
b1 #
b1 -
1&
#2195
0&
#2200
b0 ,
b100010 !
b100010 (
b100010 0
b10 .
b11110000 %
b11110000 +
b11110000 /
b1000000 $
b1000000 *
1&
#2205
0&
#2210
b1 ,
b0 .
b100010 )
1&
#2215
0&
#2220
b10 ,
b1010001 !
b1010001 (
b1010001 0
b1 .
b1 %
b1 +
b1 /
b10 #
b10 -
1&
#2225
0&
#2230
b0 ,
b110111 !
b110111 (
b110111 0
b10 .
b11110001 %
b11110001 +
b11110001 /
b1010001 $
b1010001 *
1&
#2235
0&
#2240
b1 ,
b0 .
b1011001 )
1&
#2245
0&
#2250
b10 ,
b110010 !
b110010 (
b110010 0
b1 .
b10 %
b10 +
b10 /
b11 #
b11 -
1&
#2255
0&
